Workbook

Sheet Resumo
A1: Indicador | B1: Valor
A2: Projeto | B2: None – None
A3: Versão / modo | B3: vNone / None
A4: Classe da estimativa (AACE)
A5: Data-base
A6: Custo base | B6: =Custos!D8
A7: Contingência | B7: 0
A8: Custo P50 (Monte Carlo) | B8: 0
A9: Custo P80 (Monte Carlo) | B9: 0
A10: Preço sugerido
A11: Preço mínimo (walk-away)
A12: Receita de implantação usada
A13: Origem da receita | B13: preco_sugerido
A14: Margem resultante
A15: Resultado do projeto (DRE) | B15: =DRE!B15
A16: Margem líquida (DRE) | B16: =DRE!C15
A17: Exposição máxima de caixa | B17: 0
A18: Mês do pico de exposição | B18: 2000-01
A19: Payback | B19: não ocorre no horizonte
A20: VPL ao custo de capital
A21: TIR anual
A22: Prazo provável (meses) | B22: 0
A23: Prazo P80 (dias) | B23: 0
A25: Alertas do motor
A26: custos_indiretos.overhead_pct não definido (rateio de estrutura); usado 0
A27: financeiro.custo_capital_aa não definido; custo financeiro = 0
A29: Legenda: azul = premissa dos nós; preto = fórmula; verde = vínculo entre abas. Edite os nós, não a planilha.

Sheet BOM
A1: ID | B1: Descrição | C1: Qtd | D1: Moeda | E1: Preço unit. (moeda) | F1: Câmbio | G1: Alíq. aquisição | H1: Fator calibração | I1: Total (R$) | J1: Fonte | K1: Atividade | L1: Mês pedido | M1: Mês entrega
B2: TOTAL | I2: =SUM(I2:I2)

Sheet Mao_de_obra
A1: ID | B1: Origem | C1: Perfil | D1: Categoria | E1: Horas (calibradas) | F1: Custo/hora (R$) | G1: Total (R$) | H1: Atividade
C2: TOTAL | E2: =SUM(E2:E2) | G2: =SUM(G2:G2)

Sheet Custos
A1: ID | B1: Descrição | C1: Categoria | D1: Valor (R$) | E1: Fonte
B2: Total indiretos | D2: =SUM(D2:D2)
B4: Equipamentos (BOM) | D4: =BOM!I2
B5: Mão de obra | D5: =Mao_de_obra!G2
B6: Indiretos | D6: =D2
B7: Overhead (% sobre BOM + mão de obra) | C7: 0 | D7: =C7*(D4+D5)
B8: Custo base | D8: =SUM(D4:D7)
B9: Contingência (Monte Carlo) | D9: 0
B10: Custo com contingência | D10: =D8+D9

Sheet Cronograma
A1: ID | B1: Atividade | C1: Início (dia) | D1: Fim (dia) | E1: Folga (dias) | F1: Crítica

Sheet Histograma
A1: Perfil (horas/mês)

Sheet Fluxo_de_caixa
A1: Mês | B1: Competência | C1: Receita implantacao | D1: Receita recorrente | E1: Receita operacao | F1: Impostos | G1: Comissao | H1: Equipamentos | I1: Mao de obra | J1: Indiretos | K1: Overhead | L1: Contingencia | M1: Custos recorrentes | N1: Custo variavel operacao | O1: Custo financeiro | P1: Saldo do mês | Q1: Acumulado
A2: 0 | B2: 2000-01 | C2: 0 | D2: 0 | E2: 0 | F2: 0 | G2: 0 | H2: 0 | I2: 0 | J2: 0 | K2: 0 | L2: 0 | M2: 0 | N2: 0 | O2: 0 | P2: =SUM(C2:O2) | Q2: =P2

Sheet DRE
A1: Linha | B1: Valor (R$) | C1: % receita bruta
A2: Receita bruta | B2: =SUM(Fluxo_de_caixa!C2:C2)+SUM(Fluxo_de_caixa!D2:D2)+SUM(Fluxo_de_caixa!E2:E2) | C2: =IF($B$2=0,0,B2/$B$2)
A3: (-) Impostos sobre receita | B3: =SUM(Fluxo_de_caixa!F2:F2) | C3: =IF($B$2=0,0,B3/$B$2)
A4: Receita líquida | B4: =B2+B3 | C4: =IF($B$2=0,0,B4/$B$2)
A5: (-) Equipamentos | B5: =SUM(Fluxo_de_caixa!H2:H2) | C5: =IF($B$2=0,0,B5/$B$2)
A6: (-) Mão de obra direta | B6: =SUM(Fluxo_de_caixa!I2:I2) | C6: =IF($B$2=0,0,B6/$B$2)
A7: (-) Custos recorrentes (O&M) | B7: =SUM(Fluxo_de_caixa!M2:M2) | C7: =IF($B$2=0,0,B7/$B$2)
A8: (-) Custos variáveis da operação comercial | B8: =SUM(Fluxo_de_caixa!N2:N2) | C8: =IF($B$2=0,0,B8/$B$2)
A9: Lucro bruto | B9: =B4+B5+B6+B7+B8 | C9: =IF($B$2=0,0,B9/$B$2)
A10: (-) Comissão | B10: =SUM(Fluxo_de_caixa!G2:G2) | C10: =IF($B$2=0,0,B10/$B$2)
A11: (-) Indiretos | B11: =SUM(Fluxo_de_caixa!J2:J2) | C11: =IF($B$2=0,0,B11/$B$2)
A12: (-) Overhead | B12: =SUM(Fluxo_de_caixa!K2:K2) | C12: =IF($B$2=0,0,B12/$B$2)
A13: (-) Contingência | B13: =SUM(Fluxo_de_caixa!L2:L2) | C13: =IF($B$2=0,0,B13/$B$2)
A14: Resultado operacional | B14: =B9+B10+B11+B12+B13 | C14: =IF($B$2=0,0,B14/$B$2)
A15: (-) Custo financeiro | B15: =SUM(Fluxo_de_caixa!O2:O2) | C15: =IF($B$2=0,0,B15/$B$2)
A16: Resultado do projeto | B16: =B14+B15 | C16: =IF($B$2=0,0,B16/$B$2)

Sheet Marcos
A1: ID | B1: Evento | C1: % | D1: Mês (índice) | E1: Valor (R$)

Sheet Monte_Carlo
A1: Indicador | B1: Valor
A2: iteracoes | B2: 10000
A3: custo_p10 | B3: 0
A4: custo_p50 | B4: 0
A5: custo_p80 | B5: 0
A6: custo_p90 | B6: 0
A7: prazo_p50_dias | B7: 0
A8: prazo_p80_dias | B8: 0
A10: Maiores contribuidores de incerteza

Sheet Riscos
A1: ID | B1: Descrição | C1: Categoria | D1: Probabilidade | E1: Impacto custo (provável) | F1: Impacto prazo (dias) | G1: Mitigação | H1: Dono | I1: No Monte Carlo

Sheet Premissas
A1: ID | B1: Premissa | C1: Fonte | D1: Confiança
